[
	{"book": "I", "number": 37, "title": "La Romance de Lancelot"},
	{"book": "II", "number": 37, "title": "La Joute Ancillaire"},
	{"book": "IV", "number": 26, "title": "La chambre de la Reine"},
	{"book": "IV", "number": 30, "title": "Les Bonnes"},
	{"book": "V", "number": 30, "title": "La Supplique"},
	{"book": "VI", "number": 6, "title": "Nuptiae"},
	{"book": "VI", "number": 7, "title": "Arturus Rex"},
	{"book": "VI", "number": 8, "title": "Lacrimosa"},
	{"book": "I", "number": 89, "title": "Le Fléau de Dieu"},
	{"book": "III", "number": 12, "title": "Le Fléau de Dieu II"},
	{"book": "II", "number": 68, "title": "Spiritueux"},
	{"book": "I", "number": 64, "title": "La table de Breccan"},
	{"book": "I", "number": 59, "title": "La jupe de Calogrenant"},
	{"book": "II", "number": 46, "title": "Le Cadeau"},
	{"book": "II", "number": 60, "title": "L'Alliance"},
	{"book": "VI", "number": 1, "title": "Miles Ignotus"},
	{"book": "VI", "number": 2, "title": "Centurio"},
	{"book": "VI", "number": 5, "title": "Dux bellorum"},
	{"book": "VI", "number": 8, "title": "Lacrimosa"},
	{"book": "VI", "number": 4, "title": "Arturi Inquisitio"},
	{"book": "VI", "number": 5, "title": "Dux bellorum"},
	{"book": "VI", "number": 6, "title": "Nuptiæ"},
	{"book": "VI", "number": 8, "title": "Lacrimosa"},
	{"book": "I", "number": 27, "title": "De retour de Judée"},
	{"book": "I", "number": 27, "title": "Le Retour de Judée"},
	{"book": "IV", "number": 99, "title": "Le Désordre et la Nuit"},
	{"book": "V", "number": 22, "title": "La promesse"},
	{"book": "III", "number": 98, "title": "Hollow Man"},
	{"book": "IV", "number": 2, "title": "Tous Les Matins du Monde"},
	{"book": "IV", "number": 28, "title": "La Révoquée"},
	{"book": "V", "number": 12, "title": "La roche et le fer"},
	{"book": "V", "number": 36, "title": "La Nourrice"},
	{"book": "VI", "number": 6, "title": "Nuptiæ"},
	{"book": "V", "number": 16, "title": "Les Fruits d'Hiver"},
	{"book": "V", "number": 19, "title": "Les Nocturnales"},
	{"book": "V", "number": 23, "title": "Le Forfait"},
	{"book": "I", "number": 51, "title": "Enluminures"},
	{"book": "II", "number": 45, "title": "Les Voeux"},
	{"book": "II", "number": 84, "title": "Spagenhelm"},
	{"book": "IV", "number": 14, "title": "Dagonnet et le cadastre"},
	{"book": "IV", "number": 67, "title": "Loth et le Graal"},
	{"book": "V", "number": 21, "title": "Aux yeux de tous III"},
	{"book": "VI", "number": 7, "title": "Arturus Rex"},
	{"book": "I", "number": 63, "title": "Goustan Le Cruel"},
	{"book": "I", "number": 63, "title": "Goustan le Cruel"},
	{"book": "VI", "number": 1, "title": "Miles Ignotus"},
	{"book": "VI", "number": 7, "title": "Arturus Rex"},
	{"book": "VI", "number": 7, "title": "Arturus rex"},
	{"book": "VI", "number": 8, "title": "Lacrimosa"},
	{"book": "I", "number": 22, "title": "La queue du scorpion"},
	{"book": "I", "number": 29, "title": "L’Assassin de Kaamelott"},
	{"book": "IV", "number": 53, "title": "Le Rêve d’Ygerne"},
	{"book": "II", "number": 72, "title": "L'Alliance"},
	{"book": "III", "number": 91, "title": "L’Espion"},
	{"book": "V", "number": 40, "title": "Les Pionniers"},
	{"book": "V", "number": 42, "title": "Le Destitué"},
	{"book": "VI", "number": 7, "title": "Arturus Rex"},
	{"book": "I", "number": 45, "title": "L'interprète"},
	{"book": "I", "number": 45, "title": "L’Interprète"},
	{"book": "IV", "number": 21, "title": "La Parade"},
	{"book": "V", "number": 27, "title": "Le Jurisconsulte"},
	{"book": "V", "number": 40, "title": "Les Pionniers"},
	{"book": "V", "number": 41, "title": "La Conspiratrice"},
	{"book": "VI", "number": 1, "title": "Miles Ignotus"},
	{"book": "VI", "number": 6, "title": "Nuptioe"},
	{"book": "II", "number": 20, "title": "Immaculé Karadoc"},
	{"book": "IV", "number": 26, "title": "La Chambre de la reine"},
	{"book": "VI", "number": 4, "title": "Arturi inquisitio"},
	{"book": "VI", "number": 5, "title": "Dux Bellorum"},
	{"book": "III", "number": 16, "title": "Séfriane d'Aquitaine"},
	{"book": "VI", "number": 5, "title": "Dux Bellorum"},
	{"book": "VI", "number": 8, "title": "Lacrimosa"},
	{"book": "VI", "number": 6, "title": "Nuptiæ"},
	{"book": "VI", "number": 8, "title": "Lacrimosa"},
	{"book": "VI", "number": 1, "title": "Miles Ignotus"},
	{"book": "I", "number": 59, "title": "La Visite d'Ygerne"},
	{"book": "II", "number": 69, "title": "Mater Dixit"},
	{"book": "V", "number": 24, "title": "Le dernier jour"},
	{"book": "V", "number": 69, "title": "Anton"}
]
